setup.py
Playfulbot.egg-info/PKG-INFO
Playfulbot.egg-info/SOURCES.txt
Playfulbot.egg-info/dependency_links.txt
Playfulbot.egg-info/entry_points.txt
Playfulbot.egg-info/requires.txt
Playfulbot.egg-info/top_level.txt
command_line/__init__.py
command_line/playfulbot.py