Metadata-Version: 1.0
Name: Playfulbot
Version: 1.0.8
Summary: Playfulbet auto-bet
Home-page: https://github.com/Alexsays/Playfulbot
Author: Alex Silva
Author-email: h4ll0ck at gmail dot com
License: GNU General Public License (GPLv2)
Platform: UNKNOWN
